ThaiAddressParser/__init__.py
ThaiAddressParserPlus-1.0.0.dist-info/LICENSE
ThaiAddressParserPlus-1.0.0.dist-info/METADATA
ThaiAddressParserPlus-1.0.0.dist-info/WHEEL
ThaiAddressParserPlus-1.0.0.dist-info/top_level.txt
ThaiAddressParserPlus-1.0.0.dist-info/RECORD
