Metadata-Version: 2.1
Name: ThaiAddressParserPlus
Version: 1.0.0
Summary: Thailand Address Parser
Home-page: https://github.com/dsin/ThaiAddressParserPlus
Author: Shuai Li
Author-email: li.shuai@wustl.edu
Classifier: Programming Language :: Python :: 3
Classifier: License :: OSI Approved :: MIT License
Classifier: Operating System :: OS Independent
License-File: LICENSE
Requires-Dist: bs4
Requires-Dist: requests
Requires-Dist: tqdm
